cmd_register/__init__.py
cmd_register/register.py
cmd_register-0.0.0.dist-info/LICENSE
cmd_register-0.0.0.dist-info/METADATA
cmd_register-0.0.0.dist-info/WHEEL
cmd_register-0.0.0.dist-info/top_level.txt
cmd_register-0.0.0.dist-info/RECORD
