Metadata-Version: 2.1
Name: cmd-register
Version: 0.0.0
Summary: A decorator to register functions into a container
Home-page: https://github.com/CarsonSlovoka/cmd-register
Author: Carson Tseng
Author-email: jackparadise520a@gmail.com
Classifier: Programming Language :: Python :: 3
Classifier: License :: OSI Approved :: MIT License
Requires-Python: >=3.6
License-File: LICENSE
